[
  {"character":"邦","onyomi":["ホウ"],"kunyomi":[],"meaning_vi":"nước, đất nước (cổ điển)","stroke_count":7,"vocab_examples":[{"word":"邦国","reading":"ほうこく","meaning_vi":"nước (quốc gia)"},{"word":"邦交","reading":"ほうこう","meaning_vi":"quan hệ ngoại giao"}]},
  {"character":"裏","onyomi":["リ"],"kunyomi":["うら"],"meaning_vi":"mặt trong, bên trong, lưng","stroke_count":13,"vocab_examples":[{"word":"裏切る","reading":"うらぎる","meaning_vi":"phản bội"},{"word":"裏面","reading":"りめん","meaning_vi":"mặt sau"}]},
  {"character":"肖","onyomi":["ショウ"],"kunyomi":["にる"],"meaning_vi":"giống, tương tự","stroke_count":7,"vocab_examples":[{"word":"肖像","reading":"しょうぞう","meaning_vi":"肖像"},{"word":"肖像画","reading":"しょうぞうが","meaning_vi":"tranh chân dung"}]},
  {"character":"苛","onyomi":["カ"],"kunyomi":["から","い"],"meaning_vi":"cực kỳ, khắc nghiệt, khó chịu","stroke_count":8,"vocab_examples":[{"word":"苛酷","reading":"かこく","meaning_vi":"vô cùng khắc nghiệt"},{"word":"苛烈","reading":"かれつ","meaning_vi":"dữ dội, khắc nghiệt"}]},
  {"character":"侶","onyomi":["リョ"],"kunyomi":["ともがら"],"meaning_vi":"bạn, đồng chí, cùng chung","stroke_count":8,"vocab_examples":[{"word":"侶","reading":"とも","meaning_vi":"bạn"},{"word":"法侶","reading":"ほうりょ","meaning_vi":"đạo hữu"}]},
  {"character":"遥","onyomi":["ヨウ"],"kunyomi":["はるか"],"meaning_vi":"xa xôi, rất, lâu xa","stroke_count":13,"vocab_examples":[{"word":"遥か","reading":"はるか","meaning_vi":"rất xa"},{"word":"遥か彼方","reading":"はるかかなた","meaning_vi":"quá xa"}]},
  {"character":"璃","onyomi":["リ"],"kunyomi":[],"meaning_vi":"lưu ly, đá quý (thường dùng trong tên)","stroke_count":11,"vocab_examples":[{"word":"琉璃","reading":"るり","meaning_vi":"lapis lazuli"},{"word":"水璃","reading":"すいり","meaning_vi":"thủy tinh"}]},
  {"character":"奧","onyomi":["オク"],"kunyomi":["おく"],"meaning_vi":"sâu thẳm, bên trong sâu, tối thượng","stroke_count":12,"vocab_examples":[{"word":"奧地","reading":"おくち","meaning_vi":"vùng sâu"},{"word":"奧行き","reading":"おくゆき","meaning_vi":"chiều sâu"}]},
  {"character":"昭","onyomi":["ショウ"],"kunyomi":[],"meaning_vi":"sáng, chiếu sáng, rõ ràng","stroke_count":9,"vocab_examples":[{"word":"昭和","reading":"しょうわ","meaning_vi":"Thời đại Showa"},{"word":"昭昭","reading":"しょうしょう","meaning_vi":"sáng chói"}]},
  {"character":"溶","onyomi":["ヨウ"],"kunyomi":["とける","とかす"],"meaning_vi":"tan, hòa tan, nóng chảy","stroke_count":13,"vocab_examples":[{"word":"溶液","reading":"ようえき","meaning_vi":"dung dịch"},{"word":"溶解","reading":"ようかい","meaning_vi":"hòa tan"}]},
  {"character":"稿","onyomi":["コウ"],"kunyomi":["わら"],"meaning_vi":"thảo, bản thảo, bản nháp","stroke_count":15,"vocab_examples":[{"word":"原稿","reading":"げんこう","meaning_vi":"bản thảo gốc"},{"word":"稿料","reading":"こうりょう","meaning_vi":"tiền ghi danh"}]},
  {"character":"舶","onyomi":["ハク"],"kunyomi":[],"meaning_vi":"tàu, thuyền, tàu biển","stroke_count":15,"vocab_examples":[{"word":"舶来","reading":"はくらい","meaning_vi":"nhập khẩu từ nước ngoài"},{"word":"商舶","reading":"しょうはく","meaning_vi":"tàu thương mại"}]},
  {"character":"錮","onyomi":["コ"],"kunyomi":[],"meaning_vi":"giam, phong tỏa, khoá chặt","stroke_count":16,"vocab_examples":[{"word":"錮禁","reading":"こきん","meaning_vi":"giam giữ"},{"word":"自由の錮","reading":"じゆうのこ","meaning_vi":"tự do bị giam"}]},
  {"character":"綾","onyomi":["リョウ"],"kunyomi":["あや"],"meaning_vi":"vải có vân, họa tiết, xinh đẹp","stroke_count":14,"vocab_examples":[{"word":"綾織","reading":"あやおり","meaning_vi":"vải vân"},{"word":"綾纈","reading":"りょうけち","meaning_vi":"vải nhuộm trang trí"}]},
  {"character":"縣","onyomi":["ケン"],"kunyomi":["かかる"],"meaning_vi":"treo, lủng, quan huyện (cổ)","stroke_count":13,"vocab_examples":[{"word":"縣令","reading":"けんれい","meaning_vi":"quan huyện"},{"word":"県","reading":"けん","meaning_vi":"tỉnh"}]},
  {"character":"肇","onyomi":["チョウ"],"kunyomi":["はじめる"],"meaning_vi":"khởi đầu, bắt đầu, mở đầu","stroke_count":13,"vocab_examples":[{"word":"肇始","reading":"ちょうし","meaning_vi":"khởi đầu"},{"word":"肇造","reading":"ちょうぞう","meaning_vi":"sáng lập"}]},
  {"character":"駭","onyomi":["ガイ"],"kunyomi":["おどろく"],"meaning_vi":"kinh ngạc, giật mình","stroke_count":15,"vocab_examples":[{"word":"駭然","reading":"がいぜん","meaning_vi":"kinh ngạc"},{"word":"駭動","reading":"がいどう","meaning_vi":"gây chấn động"}]},
  {"character":"誼","onyomi":["ギ"],"kunyomi":[],"meaning_vi":"thân thiện, hữu nghị, tình bạn","stroke_count":13,"vocab_examples":[{"word":"誼を結ぶ","reading":"よしみをむすぶ","meaning_vi":"kết bạn"},{"word":"国誼","reading":"こくぎ","meaning_vi":"hữu nghị quốc gia"}]},
  {"character":"蕾","onyomi":["ライ"],"kunyomi":["つぼみ"],"meaning_vi":"nụ (hoa), nụ non","stroke_count":16,"vocab_examples":[{"word":"蕾","reading":"つぼみ","meaning_vi":"nụ hoa"},{"word":"蕾蒙","reading":"らいもう","meaning_vi":"nụ non"}]},
  {"character":"蹟","onyomi":["セキ"],"kunyomi":["あと"],"meaning_vi":"dấu chân, tích tích","stroke_count":14,"vocab_examples":[{"word":"遺蹟","reading":"いせき","meaning_vi":"di tích"},{"word":"跡","reading":"あと","meaning_vi":"dấu tích"}]},
  {"character":"贖","onyomi":["ショク"],"kunyomi":[],"meaning_vi":"cứu, mua lại, trả giá","stroke_count":16,"vocab_examples":[{"word":"贖罪","reading":"しょくざい","meaning_vi":"chuộc tội"},{"word":"贖金","reading":"しょくきん","meaning_vi":"tiền chuộc"}]},
  {"character":"戚","onyomi":["セキ"],"kunyomi":["みうち"],"meaning_vi":"thân thuộc, họ hàng, buồn","stroke_count":11,"vocab_examples":[{"word":"戚友","reading":"せきゆう","meaning_vi":"bạn bè họ hàng"},{"word":"戚族","reading":"せきぞく","meaning_vi":"gia đình"}]},
  {"character":"甫","onyomi":["ホ"],"kunyomi":[],"meaning_vi":"chính, vừa mới, nhân từ","stroke_count":7,"vocab_examples":[{"word":"初甫","reading":"しょほ","meaning_vi":"lần đầu"}]},
  {"character":"牒","onyomi":["チョウ"],"kunyomi":[],"meaning_vi":"giấy tờ, giấy chứng chỉ, hồ sơ","stroke_count":13,"vocab_examples":[{"word":"牒状","reading":"ちょうじょう","meaning_vi":"giấy tờ chứng thực"},{"word":"除牒","reading":"じょちょう","meaning_vi":"giấy phát hành"}]},
  {"character":"瀆","onyomi":["トク"],"kunyomi":[],"meaning_vi":"sông nhỏ, bẩn, bả","stroke_count":19,"vocab_examples":[{"word":"瀆職","reading":"とくしょく","meaning_vi":"tham nhũng"},{"word":"玩瀆","reading":"がんとく","meaning_vi":"sỉ nhục"}]},
  {"character":"殖","onyomi":["ショク"],"kunyomi":["ふえる","ふやす"],"meaning_vi":"nhân đôi, tăng, nuôi dữ","stroke_count":11,"vocab_examples":[{"word":"植民地","reading":"しょくみんち","meaning_vi":"thuộc địa"},{"word":"殖産","reading":"しょくさん","meaning_vi":"phát triển sản xuất"}]},
  {"character":"繍","onyomi":["シュ"],"kunyomi":[],"meaning_vi":"thêu, thêu đẽo","stroke_count":19,"vocab_examples":[{"word":"繍花","reading":"しゅか","meaning_vi":"hoa thêu"},{"word":"刺繍","reading":"ししゅ","meaning_vi":"thêu đẽo"}]},
  {"character":"訣","onyomi":["ケツ"],"kunyomi":["わけ"],"meaning_vi":"bí quyết, cách thức, chia tay","stroke_count":11,"vocab_examples":[{"word":"訣別","reading":"けつべつ","meaning_vi":"chia tay"},{"word":"秘訣","reading":"ひけつ","meaning_vi":"bí quyết"}]},
  {"character":"辷","onyomi":["カツ"],"kunyomi":["すべる"],"meaning_vi":"trượt, trơn trượt","stroke_count":10,"vocab_examples":[{"word":"辷る","reading":"すべる","meaning_vi":"trượt"}]},
  {"character":"凹","onyomi":["オウ","ボ"],"kunyomi":["くぼむ","へこむ"],"meaning_vi":"lõm, sâu, lõm xõm","stroke_count":5,"vocab_examples":[{"word":"凹凸","reading":"おうとつ","meaning_vi":"凹凸"},{"word":"凹面","reading":"おうめん","meaning_vi":"mặt lõm"}]},
  {"character":"凸","onyomi":["トツ","トク"],"kunyomi":["でっぱり"],"meaning_vi":"lồi, nhô ra, nhô","stroke_count":5,"vocab_examples":[{"word":"凹凸","reading":"おうとつ","meaning_vi":"凹凸"},{"word":"凸面","reading":"とつめん","meaning_vi":"mặt lồi"}]},
  {"character":"濫","onyomi":["ラン"],"kunyomi":[],"meaning_vi":"tràn, lũ lụt, lạm, lạm dụng","stroke_count":17,"vocab_examples":[{"word":"濫用","reading":"らんよう","meaning_vi":"lạm dụng"},{"word":"濫觴","reading":"らんしょう","meaning_vi":"nguồn gốc"}]},
  {"character":"誘","onyomi":["ユウ"],"kunyomi":["さそう"],"meaning_vi":"lôi kéo, dụ dỗ, mời","stroke_count":13,"vocab_examples":[{"word":"誘引","reading":"ゆういん","meaning_vi":"lôi kéo"},{"word":"誘惑","reading":"ゆうわく","meaning_vi":"cám dỗ"}]},
  {"character":"詩","onyomi":["シ"],"kunyomi":[],"meaning_vi":"thơ, thơ ca","stroke_count":13,"vocab_examples":[{"word":"詩人","reading":"しじん","meaning_vi":"nhà thơ"},{"word":"詩集","reading":"ししゅう","meaning_vi":"tuyển thơ"}]},
  {"character":"誌","onyomi":["シ"],"kunyomi":[],"meaning_vi":"tạp chí, ghi chép, nhật ký","stroke_count":13,"vocab_examples":[{"word":"雑誌","reading":"ざっし","meaning_vi":"tạp chí"},{"word":"月誌","reading":"げっし","meaning_vi":"tạp chí hàng tháng"}]},
  {"character":"謝","onyomi":["シャ"],"kunyomi":["あやまる"],"meaning_vi":"cảm ơn, xin lỗi, từ biệt","stroke_count":12,"vocab_examples":[{"word":"謝礼","reading":"しゃれい","meaning_vi":"lời cảm ơn"},{"word":"謝罪","reading":"しゃざい","meaning_vi":"xin lỗi"}]},
  {"character":"譚","onyomi":["タン"],"kunyomi":[],"meaning_vi":"chuyện kể, câu chuyện, truyện","stroke_count":16,"vocab_examples":[{"word":"奇譚","reading":"きたん","meaning_vi":"chuyện lạ"},{"word":"逸譚","reading":"いつたん","meaning_vi":"chuyện kỳ quặc"}]},
  {"character":"讎","onyomi":["シュウ","シュ"],"kunyomi":["あだ","かたき"],"meaning_vi":"thù, kẻ thù, đối thủ","stroke_count":11,"vocab_examples":[{"word":"讎敵","reading":"しゅうてき","meaning_vi":"kẻ thù"},{"word":"宿讎","reading":"しゅくしゅう","meaning_vi":"thù cũ"}]},
  {"character":"議","onyomi":["ギ"],"kunyomi":[],"meaning_vi":"tranh luận, thảo luận, bàn","stroke_count":20,"vocab_examples":[{"word":"議論","reading":"ぎろん","meaning_vi":"tranh luận"},{"word":"会議","reading":"かいぎ","meaning_vi":"cuộc họp"}]},
  {"character":"諺","onyomi":["ゲン"],"kunyomi":[],"meaning_vi":"tục ngữ, ca dao, châm ngôn","stroke_count":16,"vocab_examples":[{"word":"諺に言う","reading":"ことわざにいう","meaning_vi":"như tục ngữ nói"}]},
  {"character":"銘","onyomi":["メイ"],"kunyomi":[],"meaning_vi":"khắc, ghi dấu, bài ca","stroke_count":14,"vocab_examples":[{"word":"銘文","reading":"めいぶん","meaning_vi":"chữ khắc"},{"word":"銘記","reading":"めいき","meaning_vi":"ghi nhớ"}]},
  {"character":"銚","onyomi":["チョウ"],"kunyomi":[],"meaning_vi":"bình rượu, bình, lọ","stroke_count":14,"vocab_examples":[{"word":"酒銚","reading":"さけちょう","meaning_vi":"bình rượu"}]},
  {"character":"鋪","onyomi":["フ"],"kunyomi":[],"meaning_vi":"quán, tiệm, shop (cổ)","stroke_count":13,"vocab_examples":[{"word":"酒鋪","reading":"さけみせ","meaning_vi":"quán rượu"},{"word":"露鋪","reading":"ろてん","meaning_vi":"tiệm"}]},
  {"character":"锞","onyomi":["ク"],"kunyomi":[],"meaning_vi":"Ku (ký hiệu hoá học)","stroke_count":12,"vocab_examples":[{"word":"锞","reading":"あきがね","meaning_vi":"đồng Ku"}]},
  {"character":"賡","onyomi":["コウ"],"kunyomi":[],"meaning_vi":"tiếp tục, tiếp nối","stroke_count":15,"vocab_examples":[{"word":"賡続","reading":"こうぞく","meaning_vi":"tiếp tục"}]},
  {"character":"蝗","onyomi":["コウ"],"kunyomi":[],"meaning_vi":"châu chấu, thầy bói (cổ)","stroke_count":15,"vocab_examples":[{"word":"蝗虫","reading":"こうちゅう","meaning_vi":"châu chấu"},{"word":"蝗害","reading":"こうがい","meaning_vi":"thiệt hại do châu chấu"}]},
  {"character":"誑","onyomi":["コウ","キョウ"],"kunyomi":[],"meaning_vi":"lừa dối, dụ dỗ, lừa","stroke_count":13,"vocab_examples":[{"word":"誑かす","reading":"たぶらかす","meaning_vi":"lừa"}]},
  {"character":"讒","onyomi":["ザン"],"kunyomi":[],"meaning_vi":"nói xấu, tố cáo, khiêu khích","stroke_count":17,"vocab_examples":[{"word":"讒言","reading":"ざんげん","meaning_vi":"lời nói xấu"},{"word":"讒訴","reading":"ざんそ","meaning_vi":"tố cáo sai"}]},
  {"character":"貲","onyomi":["し"],"kunyomi":[],"meaning_vi":"tiền tài, tài sản (cổ)","stroke_count":12,"vocab_examples":[{"word":"资财","reading":"しざい","meaning_vi":"tài sản"}]},
  {"character":"賦","onyomi":["フ"],"kunyomi":["くばる"],"meaning_vi":"phân phát, thơ phú (thể loại), thuế","stroke_count":15,"vocab_examples":[{"word":"賦役","reading":"ふえき","meaning_vi":"thuế điều"},{"word":"月賦","reading":"げっぷ","meaning_vi":"thanh toán hàng tháng"}]},
  {"character":"跚","onyomi":["サン"],"kunyomi":[],"meaning_vi":"đi lung lay, đi khập khiễng","stroke_count":12,"vocab_examples":[{"word":"蹣跚","reading":"まんさん","meaning_vi":"đi khập khiễng"}]},
  {"character":"釵","onyomi":["サイ"],"kunyomi":[],"meaning_vi":"trâm tóc, cây trâm (phụ nữ)","stroke_count":13,"vocab_examples":[{"word":"玉釵","reading":"ぎょくさい","meaning_vi":"trâm tóc ngọc"}]},
  {"character":"鐵","onyomi":["テツ"],"kunyomi":["くろがね"],"meaning_vi":"sắt, gang, bàn sắt","stroke_count":22,"vocab_examples":[{"word":"鐵道","reading":"てつどう","meaning_vi":"đường sắt"},{"word":"鐵馬","reading":"てつば","meaning_vi":"xe sắt"}]},
  {"character":"銹","onyomi":["シュ"],"kunyomi":[],"meaning_vi":"gỉ sắt, mục, phoi mục","stroke_count":13,"vocab_examples":[{"word":"銹色","reading":"しゅしょく","meaning_vi":"màu gỉ"}]}
]
